prettier_printer.py
prettier_printer-0.1.4.dist-info/LICENSE
prettier_printer-0.1.4.dist-info/METADATA
prettier_printer-0.1.4.dist-info/WHEEL
prettier_printer-0.1.4.dist-info/top_level.txt
prettier_printer-0.1.4.dist-info/RECORD
