Metadata-Version: 2.1
Name: prettier-printer
Version: 0.1.4
Summary: A syntax highlighting prettier printer for Python 3.6+
Home-page: https://github.com/maynewong/prettier_printer
Author: Mayne Wong
Author-email: maynewong1990@gmail.com
License: MIT
Platform: UNKNOWN
Classifier: License :: OSI Approved :: MIT License
Classifier: Programming Language :: Python
Classifier: Programming Language :: Python :: 3.6
Classifier: Programming Language :: Python :: Implementation :: CPython
Classifier: Programming Language :: Python :: Implementation :: PyPy
Requires-Python: >=3.6.0
Requires-Dist: pygments
